ttc/__init__.py
ttc/chatbot/__init__.py
ttc/chatbot/chatbot.py
ttc/chatbot/context.py
ttc/cli/main.py
ttc/utils.py
thomasthechatbot-1.0.5.dist-info/entry_points.txt
thomasthechatbot-1.0.5.dist-info/METADATA
thomasthechatbot-1.0.5.dist-info/WHEEL
thomasthechatbot-1.0.5.dist-info/LICENSE
thomasthechatbot-1.0.5.dist-info/RECORD
