Metadata-Version: 2.1
Name: thomasthechatbot
Version: 1.0.5
Summary: A Python chatbot that learns as you speak to it.
Home-page: https://github.com/principle105/thomasthechatbot
License: MIT
Keywords: chatbot
Author: principle105
Author-email: principle105@gmail.com
Requires-Python: >=3.9,<4.0
Classifier: License :: OSI Approved :: MIT License
Classifier: Programming Language :: Python :: 3
Classifier: Programming Language :: Python :: 3.9
Classifier: Programming Language :: Python :: 3.10
Classifier: Programming Language :: Python :: 3.11
Requires-Dist: contractions (>=0.1.72,<0.2.0)
Requires-Dist: inquirerpy (>=0.3.4,<0.4.0)
Requires-Dist: nltk (>=3.7,<4.0)
Requires-Dist: pyspellchecker (>=0.7.0,<0.8.0)
Requires-Dist: typer (>=0.6.1,<0.7.0)
Requires-Dist: yaspin (>=2.2.0,<3.0.0)
Project-URL: Repository, https://github.com/principle105/thomasthechatbot
